docs/Figures/combiner.py
docs/Figures/resizer.py
docs/source/conf.py
paper/examplescript.py
paper/fracgrad_equation.py
paper/sensitivity_analysis.py
stresslog/BoreStab.py
stresslog/DrawSP.py
stresslog/PlotVec.py
stresslog/Plotter.py
stresslog/__init__.py
stresslog/__main__.py
stresslog/failure_criteria.py
stresslog/forecast.py
stresslog/geomechanics.py
stresslog/hydraulics.py
stresslog/obgppshmin.py
stresslog/plotangle.py
stresslog/syntheticLogs.py
stresslog/thirdparty.py
stresslog/unit_converter.py
stresslog-1.7.8.dist-info/licenses/LICENSE
tests/test_package.py
tests/test_units_stresslog.py
stresslog-1.7.8.dist-info/METADATA
stresslog-1.7.8.dist-info/WHEEL
stresslog-1.7.8.dist-info/top_level.txt
stresslog-1.7.8.dist-info/RECORD
