Metadata-Version: 2.4
Name: stresslog
Version: 1.7.8
Summary: Library for stress calculations from well logs
Home-page: https://www.rocklab.in/stresslog
Author: Arkadeep Ghosh
Author-email: Arkadeep Ghosh <arkadeep_ghosh@rocklab.in>
License: AGPL-3.0
Project-URL: Homepage, https://www.rocklab.in/stresslog
Project-URL: Documentation, https://stresslog.readthedocs.io/en/stable/
Project-URL: Source, https://github.com/GeoArkadeep/Stresslog
Requires-Python: >=3.10,<=3.14
License-File: LICENSE
Requires-Dist: pandas>=2.0
Requires-Dist: numpy>=2.0.0
Requires-Dist: scipy
Requires-Dist: welly
Requires-Dist: pint
Requires-Dist: matplotlib
Requires-Dist: plotly
Requires-Dist: dlisio
Requires-Dist: setuptools<81,>=42
Dynamic: author
Dynamic: home-page
Dynamic: license-file
Dynamic: requires-python
